metadata_converter
templates
tests
