Metadata-Version: 2.1
Name: exchange-metadata-converter
Version: 0.0.9
Summary: exchange metadata converters
Home-page: https://github.com/CODAIT/exchange-metadata-converter
Author: CODAIT
Author-email: ptitzler@us.ibm.com
License: Apache-2.0
Keywords: YAML templating engine
Platform: UNKNOWN
Classifier: Development Status :: 3 - Alpha
Classifier: License :: OSI Approved :: Apache Software License
Classifier: Programming Language :: Python :: 3.6
Classifier: Programming Language :: Python :: 3.7
Classifier: Programming Language :: Python :: 3.8
